LICENSE
htmls_to_datasette/__main__.py
htmls_to_datasette/cli.py
htmls_to_datasette-0.1.2.dist-info/entry_points.txt
htmls_to_datasette-0.1.2.dist-info/LICENSE
htmls_to_datasette-0.1.2.dist-info/WHEEL
htmls_to_datasette-0.1.2.dist-info/METADATA
htmls_to_datasette-0.1.2.dist-info/RECORD
